<?xml version="1.0" encoding="UTF-8"?>

<quakeml xmlns="http://quakeml.org/xmlns/quakeml/1.2">
  <eventParameters publicID="smi:ISC/bulletin">
    <creationInfo>
      <agencyID>ISC</agencyID>
      <creationTime>2021-04-14T11:37:14</creationTime>
    </creationInfo>
    <description>Reviewed ISC Bulletin</description>
    <event publicID="smi:ISC/evid=611831635">
      <preferredOriginID>smi:ISC/origid=611974391</preferredOriginID>
      <description>
        <text>Bougainville-Solomon Islands region</text>
        <type>Flinn-Engdahl region</type>
      </description>
      <type>earthquake</type>
      <typeCertainty>suspected</typeCertainty>
      <origin publicID="smi:ISC/origid=611974391">
        <time>
          <value>2017-01-22T04:30:24.61Z</value>
          <uncertainty>0.23</uncertainty>
        </time>
        <latitude>
          <value>-6.2273</value>
        </latitude>
        <longitude>
          <value>155.0743</value>
        </longitude>
        <depth>
          <value>156535.3</value>
        </depth>
        <quality>
          <usedPhaseCount>2982</usedPhaseCount>
          <associatedStationCount>2693</associatedStationCount>
          <standardError>1.9232</standardError>
          <azimuthalGap>6.583</azimuthalGap>
          <minimumDistance>3.535</minimumDistance>
          <maximumDistance>163.770</maximumDistance>
        </quality>
        <creationInfo>
          <author>ISC</author>
        </creationInfo>
        <originUncertainty>
          <preferredDescription>uncertainty ellipse</preferredDescription>
          <minHorizontalUncertainty>3136.6</minHorizontalUncertainty>
          <maxHorizontalUncertainty>3981.65</maxHorizontalUncertainty>
          <azimuthMaxHorizontalUncertainty>56.5</azimuthMaxHorizontalUncertainty>
        </originUncertainty>
      </origin>
      <origin publicID="smi:ISC/origid=608560631">
        <time>
          <value>2017-01-22T04:30:22.40Z</value>
          <uncertainty>0.00</uncertainty>
        </time>
        <latitude>
          <value>-6.1900</value>
        </latitude>
        <longitude>
          <value>155.1400</value>
        </longitude>
        <depth>
          <value>160000.0</value>
        </depth>
        <quality>
          <usedPhaseCount>1</usedPhaseCount>
          <standardError>1.0600</standardError>
          <azimuthalGap>320.000</azimuthalGap>
          <minimumDistance>47.500</minimumDistance>
          <maximumDistance>85.800</maximumDistance>
        </quality>
        <creationInfo>
          <author>BJI</author>
        </creationInfo>
      </origin>
      <origin publicID="smi:ISC/origid=611621490">
        <time>
          <value>2017-01-22T04:30:22.70Z</value>
          <uncertainty>0.91</uncertainty>
        </time>
        <latitude>
          <value>-6.1840</value>
        </latitude>
        <longitude>
          <value>154.9950</value>
        </longitude>
        <depth>
          <value>155000.0</value>
        </depth>
        <quality>
          <usedPhaseCount>213</usedPhaseCount>
        </quality>
        <creationInfo>
          <author>MOS</author>
        </creationInfo>
        <originUncertainty>
          <preferredDescription>uncertainty ellipse</preferredDescription>
          <minHorizontalUncertainty>4800</minHorizontalUncertainty>
          <maxHorizontalUncertainty>6900</maxHorizontalUncertainty>
          <azimuthMaxHorizontalUncertainty>112.8</azimuthMaxHorizontalUncertainty>
        </originUncertainty>
      </origin>
      <origin publicID="smi:ISC/origid=608433036">
        <time>
          <value>2017-01-22T04:30:22.96Z</value>
          <uncertainty>2.48</uncertainty>
        </time>
        <latitude>
          <value>-6.2464</value>
        </latitude>
        <longitude>
          <value>155.1718</value>
        </longitude>
        <depth>
          <value>135000.0</value>
        </depth>
        <depthType>operator assigned</depthType>
        <quality>
          <usedPhaseCount>321</usedPhaseCount>
          <standardError>1.2200</standardError>
          <azimuthalGap>9.000</azimuthalGap>
          <minimumDistance>3.625</minimumDistance>
        </quality>
        <creationInfo>
          <author>NEIC</author>
        </creationInfo>
        <originUncertainty>
          <preferredDescription>uncertainty ellipse</preferredDescription>
          <minHorizontalUncertainty>10000</minHorizontalUncertainty>
          <maxHorizontalUncertainty>12400</maxHorizontalUncertainty>
          <azimuthMaxHorizontalUncertainty>214.0</azimuthMaxHorizontalUncertainty>
        </originUncertainty>
      </origin>
      <origin publicID="smi:ISC/origid=608175233">
        <time>
          <value>2017-01-22T04:30:23.54Z</value>
          <uncertainty>0.89</uncertainty>
        </time>
        <latitude>
          <value>-6.2000</value>
        </latitude>
        <longitude>
          <value>155.0673</value>
        </longitude>
        <depth>
          <value>148000.0</value>
        </depth>
        <quality>
          <usedPhaseCount>126</usedPhaseCount>
          <standardError>0.8000</standardError>
          <azimuthalGap>21.000</azimuthalGap>
          <minimumDistance>3.560</minimumDistance>
          <maximumDistance>163.790</maximumDistance>
        </quality>
        <creationInfo>
          <author>IDC</author>
        </creationInfo>
        <originUncertainty>
          <preferredDescription>uncertainty ellipse</preferredDescription>
          <minHorizontalUncertainty>5300</minHorizontalUncertainty>
          <maxHorizontalUncertainty>7000</maxHorizontalUncertainty>
          <azimuthMaxHorizontalUncertainty>57.0</azimuthMaxHorizontalUncertainty>
        </originUncertainty>
      </origin>
      <origin publicID="smi:ISC/origid=613870078">
        <time>
          <value>2017-01-22T04:30:24.00Z</value>
        </time>
        <latitude>
          <value>-6.2670</value>
        </latitude>
        <longitude>
          <value>155.1190</value>
        </longitude>
        <depth>
          <value>149000.0</value>
        </depth>
        <creationInfo>
          <author>IPGP</author>
        </creationInfo>
      </origin>
      <origin publicID="smi:ISC/origid=611801920">
        <time>
          <value>2017-01-22T04:30:24.90Z</value>
          <uncertainty>0.40</uncertainty>
        </time>
        <latitude>
          <value>-6.1700</value>
        </latitude>
        <longitude>
          <value>155.0300</value>
        </longitude>
        <depth>
          <value>163000.0</value>
        </depth>
        <quality>
          <standardError>1.4200</standardError>
          <azimuthalGap>54.000</azimuthalGap>
        </quality>
        <creationInfo>
          <author>DJA</author>
        </creationInfo>
      </origin>
      <origin publicID="smi:ISC/origid=611768912">
        <time>
          <value>2017-01-22T04:30:25Z</value>
        </time>
        <latitude>
          <value>-6.0490</value>
        </latitude>
        <longitude>
          <value>155.2880</value>
        </longitude>
        <depth>
          <value>166400.0</value>
        </depth>
        <creationInfo>
          <author>KLM</author>
        </creationInfo>
      </origin>
      <origin publicID="smi:ISC/origid=614730897">
        <time>
          <value>2017-01-22T04:30:25.33Z</value>
        </time>
        <latitude>
          <value>-6.2200</value>
        </latitude>
        <longitude>
          <value>155.0430</value>
        </longitude>
        <depth>
          <value>167900.0</value>
        </depth>
        <quality>
          <usedPhaseCount>1619</usedPhaseCount>
          <associatedStationCount>999</associatedStationCount>
          <standardError>1.0400</standardError>
        </quality>
        <creationInfo>
          <author>ISC-EHB</author>
        </creationInfo>
        <originUncertainty>
          <preferredDescription>uncertainty ellipse</preferredDescription>
          <minHorizontalUncertainty>1700</minHorizontalUncertainty>
          <maxHorizontalUncertainty>1700</maxHorizontalUncertainty>
          <azimuthMaxHorizontalUncertainty>109.0</azimuthMaxHorizontalUncertainty>
        </originUncertainty>
      </origin>
      <origin publicID="smi:ISC/origid=608529182">
        <time>
          <value>2017-01-22T04:30:38.00Z</value>
          <uncertainty>0.10</uncertainty>
        </time>
        <latitude>
          <value>-6.0300</value>
        </latitude>
        <longitude>
          <value>154.9400</value>
        </longitude>
        <depth>
          <value>149600.0</value>
        </depth>
        <epicenterFixed>1</epicenterFixed>
        <quality>
          <usedPhaseCount>1470</usedPhaseCount>
          <associatedStationCount>171</associatedStationCount>
        </quality>
        <type>centroid</type>
        <creationInfo>
          <author>GCMT</author>
        </creationInfo>
      </origin>
      <origin publicID="smi:ISC/origid=608433040">
        <time>
          <value>2017-01-22T04:30:54.20Z</value>
        </time>
        <latitude>
          <value>-6.0535</value>
        </latitude>
        <longitude>
          <value>154.3923</value>
        </longitude>
        <depth>
          <value>145300.0</value>
        </depth>
        <type>centroid</type>
        <creationInfo>
          <author>NEIC</author>
        </creationInfo>
      </origin>
      <origin publicID="smi:ISC/origid=608433042">
        <time>
          <value>2017-01-22T04:31:04.70Z</value>
        </time>
        <latitude>
          <value>-6.2087</value>
        </latitude>
        <longitude>
          <value>154.9289</value>
        </longitude>
        <depth>
          <value>140500.0</value>
        </depth>
        <type>centroid</type>
        <creationInfo>
          <author>NEIC</author>
        </creationInfo>
      </origin>
      <focalMechanism publicID="smi:ISC/fault_planes;fmid=600248154">
        <nodalPlanes>
          <nodalPlane1>
            <strike>
              <value>130.83</value>
            </strike>
            <dip>
              <value>50.49</value>
            </dip>
            <rake>
              <value>97.72</value>
            </rake>
          </nodalPlane1>
          <nodalPlane2>
            <strike>
              <value>298.81</value>
            </strike>
            <dip>
              <value>40.13</value>
            </dip>
            <rake>
              <value>80.75</value>
            </rake>
          </nodalPlane2>
        </nodalPlanes>
        <principalAxes>
          <tAxis>
            <azimuth>
              <value>84.0000</value>
            </azimuth>
            <plunge>
              <value>82.0000</value>
            </plunge>
            <length>
              <value>9.267e+20</value>
            </length>
          </tAxis>
          <pAxis>
            <azimuth>
              <value>215.0000</value>
            </azimuth>
            <plunge>
              <value>5.0000</value>
            </plunge>
            <length>
              <value>-8.695e+20</value>
            </length>
          </pAxis>
          <nAxis>
            <azimuth>
              <value>306.0000</value>
            </azimuth>
            <plunge>
              <value>6.0000</value>
            </plunge>
            <length>
              <value>-5.720e+19</value>
            </length>
          </nAxis>
        </principalAxes>
        <creationInfo>
          <author>NEIC</author>
        </creationInfo>
        <momentTensor publicID="smi:ISC/moment_tensor;fmid=600248154">
          <derivedOriginID>smi:ISC/origid=608433042</derivedOriginID>
          <scalarMoment>
            <value>8.980e+20</value>
          </scalarMoment>
          <tensor>
            <Mrr>
              <value>9.014e+20</value>
              <uncertainty>1.000e+30</uncertainty>
            </Mrr>
            <Mtt>
              <value>-5.928e+20</value>
              <uncertainty>1.000e+30</uncertainty>
            </Mtt>
            <Mpp>
              <value>-3.086e+20</value>
              <uncertainty>1.000e+30</uncertainty>
            </Mpp>
            <Mrt>
              <value>7.299e+19</value>
              <uncertainty>1.000e+30</uncertainty>
            </Mrt>
            <Mrp>
              <value>-1.761e+20</value>
              <uncertainty>1.000e+30</uncertainty>
            </Mrp>
            <Mtp>
              <value>3.784e+20</value>
              <uncertainty>1.000e+30</uncertainty>
            </Mtp>
          </tensor>
          <clvd>0.1235</clvd>
          <sourceTimeFunction>
            <type>unknown</type>
            <duration>46.22000</duration>
          </sourceTimeFunction>
        </momentTensor>
      </focalMechanism>
      <focalMechanism publicID="smi:ISC/fault_planes;fmid=600612207">
        <triggeringOriginID>smi:ISC/origid=613870078</triggeringOriginID>
        <nodalPlanes>
          <nodalPlane1>
            <strike>
              <value>140.00</value>
            </strike>
            <dip>
              <value>51.00</value>
            </dip>
            <rake>
              <value>98.00</value>
            </rake>
          </nodalPlane1>
          <nodalPlane2>
            <strike>
              <value>307.00</value>
            </strike>
            <dip>
              <value>40.00</value>
            </dip>
            <rake>
              <value>80.00</value>
            </rake>
          </nodalPlane2>
        </nodalPlanes>
        <creationInfo>
          <author>IPGP</author>
        </creationInfo>
      </focalMechanism>
      <focalMechanism publicID="smi:ISC/fault_planes;fmid=600248153">
        <nodalPlanes>
          <nodalPlane1>
            <strike>
              <value>129.39</value>
            </strike>
            <dip>
              <value>48.90</value>
            </dip>
            <rake>
              <value>95.39</value>
            </rake>
          </nodalPlane1>
          <nodalPlane2>
            <strike>
              <value>301.23</value>
            </strike>
            <dip>
              <value>41.39</value>
            </dip>
            <rake>
              <value>83.86</value>
            </rake>
          </nodalPlane2>
        </nodalPlanes>
        <principalAxes>
          <tAxis>
            <azimuth>
              <value>83.0000</value>
            </azimuth>
            <plunge>
              <value>84.0000</value>
            </plunge>
            <length>
              <value>9.590e+20</value>
            </length>
          </tAxis>
          <pAxis>
            <azimuth>
              <value>216.0000</value>
            </azimuth>
            <plunge>
              <value>4.0000</value>
            </plunge>
            <length>
              <value>-9.192e+20</value>
            </length>
          </pAxis>
          <nAxis>
            <azimuth>
              <value>306.0000</value>
            </azimuth>
            <plunge>
              <value>4.0000</value>
            </plunge>
            <length>
              <value>-3.982e+19</value>
            </length>
          </nAxis>
        </principalAxes>
        <creationInfo>
          <author>NEIC</author>
        </creationInfo>
        <momentTensor publicID="smi:ISC/moment_tensor;fmid=600248153">
          <derivedOriginID>smi:ISC/origid=608433040</derivedOriginID>
          <scalarMoment>
            <value>9.390e+20</value>
          </scalarMoment>
          <tensor>
            <Mrr>
              <value>9.459e+20</value>
              <uncertainty>1.000e+30</uncertainty>
            </Mrr>
            <Mtt>
              <value>-6.189e+20</value>
              <uncertainty>1.000e+30</uncertainty>
            </Mtt>
            <Mpp>
              <value>-3.270e+20</value>
              <uncertainty>1.000e+30</uncertainty>
            </Mpp>
            <Mrt>
              <value>5.881e+19</value>
              <uncertainty>1.000e+30</uncertainty>
            </Mrt>
            <Mrp>
              <value>-1.287e+20</value>
              <uncertainty>1.000e+30</uncertainty>
            </Mrp>
            <Mtp>
              <value>4.132e+20</value>
              <uncertainty>1.000e+30</uncertainty>
            </Mtp>
          </tensor>
          <clvd>0.0831</clvd>
          <sourceTimeFunction>
            <type>unknown</type>
            <duration>50.36000</duration>
          </sourceTimeFunction>
        </momentTensor>
      </focalMechanism>
      <focalMechanism publicID="smi:ISC/fault_planes;fmid=600251723">
        <nodalPlanes>
          <nodalPlane1>
            <strike>
              <value>129.00</value>
            </strike>
            <dip>
              <value>51.00</value>
            </dip>
            <rake>
              <value>97.00</value>
            </rake>
          </nodalPlane1>
          <nodalPlane2>
            <strike>
              <value>298.00</value>
            </strike>
            <dip>
              <value>40.00</value>
            </dip>
            <rake>
              <value>81.00</value>
            </rake>
          </nodalPlane2>
        </nodalPlanes>
        <principalAxes>
          <tAxis>
            <azimuth>
              <value>81.0000</value>
            </azimuth>
            <plunge>
              <value>82.0000</value>
            </plunge>
            <length>
              <value>8.670e+20</value>
            </length>
          </tAxis>
          <pAxis>
            <azimuth>
              <value>214.0000</value>
            </azimuth>
            <plunge>
              <value>6.0000</value>
            </plunge>
            <length>
              <value>-8.560e+20</value>
            </length>
          </pAxis>
          <nAxis>
            <azimuth>
              <value>305.0000</value>
            </azimuth>
            <plunge>
              <value>6.0000</value>
            </plunge>
            <length>
              <value>-1.100e+19</value>
            </length>
          </nAxis>
        </principalAxes>
        <methodID>smi:ISC/methodID=Best_double_couple</methodID>
        <creationInfo>
          <author>GCMT</author>
        </creationInfo>
        <momentTensor publicID="smi:ISC/moment_tensor;fmid=600251723">
          <derivedOriginID>smi:ISC/origid=608529182</derivedOriginID>
          <scalarMoment>
            <value>8.620e+20</value>
          </scalarMoment>
          <tensor>
            <Mrr>
              <value>8.420e+20</value>
              <uncertainty>2.000e+18</uncertainty>
            </Mrr>
            <Mtt>
              <value>-5.840e+20</value>
              <uncertainty>1.000e+18</uncertainty>
            </Mtt>
            <Mpp>
              <value>-2.500e+20</value>
              <uncertainty>1.000e+18</uncertainty>
            </Mpp>
            <Mrt>
              <value>8.700e+19</value>
              <uncertainty>2.000e+18</uncertainty>
            </Mrt>
            <Mrp>
              <value>-1.660e+20</value>
              <uncertainty>1.000e+18</uncertainty>
            </Mrp>
            <Mtp>
              <value>3.860e+20</value>
              <uncertainty>1.000e+18</uncertainty>
            </Mtp>
          </tensor>
          <sourceTimeFunction>
            <type>unknown</type>
            <duration>21.5</duration>
          </sourceTimeFunction>
        </momentTensor>
      </focalMechanism>
      <focalMechanism publicID="smi:ISC/fault_planes;fmid=600446060">
        <triggeringOriginID>smi:ISC/origid=611621490</triggeringOriginID>
        <nodalPlanes>
          <nodalPlane1>
            <strike>
              <value>135.00</value>
            </strike>
            <dip>
              <value>58.00</value>
            </dip>
            <rake>
              <value>101.00</value>
            </rake>
          </nodalPlane1>
          <nodalPlane2>
            <strike>
              <value>294.00</value>
            </strike>
            <dip>
              <value>33.00</value>
            </dip>
            <rake>
              <value>73.00</value>
            </rake>
          </nodalPlane2>
        </nodalPlanes>
        <creationInfo>
          <author>MOS</author>
        </creationInfo>
      </focalMechanism>
      <focalMechanism publicID="smi:ISC/fault_planes;fmid=600491955">
        <triggeringOriginID>smi:ISC/origid=611974391</triggeringOriginID>
        <nodalPlanes>
          <nodalPlane1>
            <strike>
              <value>115.67</value>
            </strike>
            <dip>
              <value>73.26</value>
            </dip>
            <rake>
              <value>115.07</value>
            </rake>
          </nodalPlane1>
          <nodalPlane2>
            <strike>
              <value>237.29</value>
            </strike>
            <dip>
              <value>29.84</value>
            </dip>
            <rake>
              <value>35.37</value>
            </rake>
          </nodalPlane2>
        </nodalPlanes>
        <methodID>smi:ISC/methodID=First_motions</methodID>
        <creationInfo>
          <author>ISC</author>
        </creationInfo>
      </focalMechanism>
      <focalMechanism publicID="smi:ISC/fault_planes;fmid=600248152">
        <triggeringOriginID>smi:ISC/origid=608433036</triggeringOriginID>
        <nodalPlanes>
          <nodalPlane1>
            <strike>
              <value>132.34</value>
            </strike>
            <dip>
              <value>49.40</value>
            </dip>
            <rake>
              <value>92.16</value>
            </rake>
          </nodalPlane1>
          <nodalPlane2>
            <strike>
              <value>309.02</value>
            </strike>
            <dip>
              <value>40.65</value>
            </dip>
            <rake>
              <value>87.48</value>
            </rake>
          </nodalPlane2>
        </nodalPlanes>
        <principalAxes>
          <tAxis>
            <azimuth>
              <value>61.0000</value>
            </azimuth>
            <plunge>
              <value>85.0000</value>
            </plunge>
            <length>
              <value>7.973e+20</value>
            </length>
          </tAxis>
          <pAxis>
            <azimuth>
              <value>221.0000</value>
            </azimuth>
            <plunge>
              <value>4.0000</value>
            </plunge>
            <length>
              <value>-7.291e+20</value>
            </length>
          </pAxis>
          <nAxis>
            <azimuth>
              <value>311.0000</value>
            </azimuth>
            <plunge>
              <value>2.0000</value>
            </plunge>
            <length>
              <value>-6.821e+19</value>
            </length>
          </nAxis>
        </principalAxes>
        <creationInfo>
          <author>NEIC</author>
        </creationInfo>
        <momentTensor publicID="smi:ISC/moment_tensor;fmid=600248152">
          <scalarMoment>
            <value>7.650e+20</value>
          </scalarMoment>
          <tensor>
            <Mrr>
              <value>7.877e+20</value>
              <uncertainty>1.000e+30</uncertainty>
            </Mrr>
            <Mtt>
              <value>-4.434e+20</value>
              <uncertainty>1.000e+30</uncertainty>
            </Mtt>
            <Mpp>
              <value>-3.444e+20</value>
              <uncertainty>1.000e+30</uncertainty>
            </Mpp>
            <Mrt>
              <value>7.168e+19</value>
              <uncertainty>1.000e+30</uncertainty>
            </Mrt>
            <Mrp>
              <value>-9.459e+19</value>
              <uncertainty>1.000e+30</uncertainty>
            </Mrp>
            <Mtp>
              <value>3.226e+20</value>
              <uncertainty>1.000e+30</uncertainty>
            </Mtp>
          </tensor>
          <clvd>0.1711</clvd>
        </momentTensor>
      </focalMechanism>
      <magnitude publicID="smi:ISC/magid=617492147">
        <mag>
          <value>7.15</value>
        </mag>
        <type>mb</type>
        <originID>smi:ISC/origid=611974391</originID>
        <stationCount>472</stationCount>
        <creationInfo>
          <author>ISC</author>
        </creationInfo>
      </magnitude>
      <magnitude publicID="smi:ISC/magid=611478046">
        <mag>
          <value>6.60</value>
        </mag>
        <type>mb</type>
        <originID>smi:ISC/origid=608560631</originID>
        <stationCount>80</stationCount>
        <creationInfo>
          <author>BJI</author>
        </creationInfo>
      </magnitude>
      <magnitude publicID="smi:ISC/magid=611478045">
        <mag>
          <value>7.80</value>
        </mag>
        <type>mB</type>
        <originID>smi:ISC/origid=608560631</originID>
        <stationCount>68</stationCount>
        <creationInfo>
          <author>BJI</author>
        </creationInfo>
      </magnitude>
      <magnitude publicID="smi:ISC/magid=616528050">
        <mag>
          <value>7.10</value>
        </mag>
        <type>mb</type>
        <originID>smi:ISC/origid=611621490</originID>
        <stationCount>52</stationCount>
        <creationInfo>
          <author>MOS</author>
        </creationInfo>
      </magnitude>
      <magnitude publicID="smi:ISC/magid=616528049">
        <mag>
          <value>7.40</value>
        </mag>
        <type>MS</type>
        <originID>smi:ISC/origid=611621490</originID>
        <stationCount>18</stationCount>
        <creationInfo>
          <author>MOS</author>
        </creationInfo>
      </magnitude>
      <magnitude publicID="smi:ISC/magid=611333682">
        <mag>
          <value>7.20</value>
        </mag>
        <type>mb</type>
        <originID>smi:ISC/origid=608433036</originID>
        <stationCount>490</stationCount>
        <creationInfo>
          <author>NEIC</author>
        </creationInfo>
      </magnitude>
      <magnitude publicID="smi:ISC/magid=611333683">
        <mag>
          <value>7.90</value>
        </mag>
        <type>Mwb</type>
        <originID>smi:ISC/origid=608433036</originID>
        <stationCount>46</stationCount>
        <creationInfo>
          <author>NEIC</author>
        </creationInfo>
      </magnitude>
      <magnitude publicID="smi:ISC/magid=611333684">
        <mag>
          <value>7.90</value>
        </mag>
        <type>Mwc</type>
        <originID>smi:ISC/origid=608433036</originID>
        <stationCount>144</stationCount>
        <creationInfo>
          <author>NEIC</author>
        </creationInfo>
      </magnitude>
      <magnitude publicID="smi:ISC/magid=611333685">
        <mag>
          <value>7.90</value>
        </mag>
        <type>Mww</type>
        <originID>smi:ISC/origid=608433036</originID>
        <stationCount>54</stationCount>
        <creationInfo>
          <author>NEIC</author>
        </creationInfo>
      </magnitude>
      <magnitude publicID="smi:ISC/magid=611062618">
        <mag>
          <value>6.20</value>
        </mag>
        <type>mb</type>
        <originID>smi:ISC/origid=608175233</originID>
        <stationCount>52</stationCount>
        <creationInfo>
          <author>IDC</author>
        </creationInfo>
      </magnitude>
      <magnitude publicID="smi:ISC/magid=611062619">
        <mag>
          <value>6.60</value>
        </mag>
        <type>mbtmp</type>
        <originID>smi:ISC/origid=608175233</originID>
        <stationCount>55</stationCount>
        <creationInfo>
          <author>IDC</author>
        </creationInfo>
      </magnitude>
      <magnitude publicID="smi:ISC/magid=611062620">
        <mag>
          <value>7.40</value>
        </mag>
        <type>MS</type>
        <originID>smi:ISC/origid=608175233</originID>
        <stationCount>34</stationCount>
        <creationInfo>
          <author>IDC</author>
        </creationInfo>
      </magnitude>
      <magnitude publicID="smi:ISC/magid=619939220">
        <mag>
          <value>7.90</value>
        </mag>
        <type>Mw</type>
        <originID>smi:ISC/origid=613870078</originID>
        <creationInfo>
          <author>IPGP</author>
        </creationInfo>
      </magnitude>
      <magnitude publicID="smi:ISC/magid=616772650">
        <mag>
          <value>7.23</value>
        </mag>
        <type>mb</type>
        <originID>smi:ISC/origid=611801920</originID>
        <stationCount>140</stationCount>
        <creationInfo>
          <author>DJA</author>
        </creationInfo>
      </magnitude>
      <magnitude publicID="smi:ISC/magid=616772649">
        <mag>
          <value>7.79</value>
        </mag>
        <type>mB</type>
        <originID>smi:ISC/origid=611801920</originID>
        <stationCount>139</stationCount>
        <creationInfo>
          <author>DJA</author>
        </creationInfo>
      </magnitude>
      <magnitude publicID="smi:ISC/magid=616772648">
        <mag>
          <value>7.86</value>
        </mag>
        <type>Mw</type>
        <originID>smi:ISC/origid=611801920</originID>
        <stationCount>99</stationCount>
        <creationInfo>
          <author>DJA</author>
        </creationInfo>
      </magnitude>
      <magnitude publicID="smi:ISC/magid=616772654">
        <mag>
          <value>7.42</value>
        </mag>
        <type>Mwp</type>
        <originID>smi:ISC/origid=611801920</originID>
        <stationCount>135</stationCount>
        <creationInfo>
          <author>DJA</author>
        </creationInfo>
      </magnitude>
      <magnitude publicID="smi:ISC/magid=611429247">
        <mag>
          <value>7.89</value>
        </mag>
        <type>MW</type>
        <originID>smi:ISC/origid=608529182</originID>
        <stationCount>171</stationCount>
        <creationInfo>
          <author>GCMT</author>
        </creationInfo>
      </magnitude>
    </event>
  </eventParameters>
</quakeml>
